flask_pydantic_openapi/__init__.py
flask_pydantic_openapi/config.py
flask_pydantic_openapi/flask_backend.py
flask_pydantic_openapi/page.py
flask_pydantic_openapi/spec.py
flask_pydantic_openapi/types.py
flask_pydantic_openapi/utils.py
flask_pydantic_openapi-0.4.2.dist-info/LICENSE
flask_pydantic_openapi-0.4.2.dist-info/METADATA
flask_pydantic_openapi-0.4.2.dist-info/WHEEL
flask_pydantic_openapi-0.4.2.dist-info/entry_points.txt
flask_pydantic_openapi-0.4.2.dist-info/top_level.txt
flask_pydantic_openapi-0.4.2.dist-info/RECORD
