Metadata-Version: 2.1
Name: flask-pydantic-openapi
Version: 0.4.2
Summary: generate OpenAPI document and validate request & response with Python annotations.
Home-page: https://github.com/PostBeyond/flask-pydantic-spec
Author: Chris Gearing, Simon Hayward, Rob Young, Donald Fleming, Saurabh Jha
Author-email: chris.gearing@turntown.digital
License: UNKNOWN
Platform: UNKNOWN
Classifier: Programming Language :: Python :: 3 :: Only
Classifier: Programming Language :: Python :: 3.7
Classifier: Programming Language :: Python :: 3.8
Classifier: Programming Language :: Python :: 3.9
Classifier: Programming Language :: Python :: 3.10
Classifier: Programming Language :: Python :: 3.11
Classifier: Operating System :: OS Independent
Classifier: Topic :: Software Development :: Libraries :: Python Modules
Requires-Python: >=3.7
Requires-Dist: pydantic (<2,>=1.2)
Requires-Dist: inflection (<1,>=0.5.0)
Requires-Dist: nested-lookup (<1,>=0.2.21)
Provides-Extra: flask
Requires-Dist: flask ; extra == 'flask'
